odoo/addons/ssi_product_website/README.rst
odoo/addons/ssi_product_website/__init__.py
odoo/addons/ssi_product_website/__manifest__.py
odoo/addons/ssi_product_website/controllers/__init__.py
odoo/addons/ssi_product_website/controllers/main.py
odoo/addons/ssi_product_website/data/data.xml
odoo/addons/ssi_product_website/models/__init__.py
odoo/addons/ssi_product_website/models/product_template.py
odoo/addons/ssi_product_website/security/ir.model.access.csv
odoo/addons/ssi_product_website/static/description/icon.png
odoo/addons/ssi_product_website/static/src/scss/primary_variables.scss
odoo/addons/ssi_product_website/static/src/scss/ssi_product_website.scss
odoo/addons/ssi_product_website/static/src/scss/ssi_product_website_frontend.scss
odoo/addons/ssi_product_website/views/product_template_views.xml
odoo/addons/ssi_product_website/views/templates.xml
odoo14_addon_ssi_product_website-14.0.1.2.0.dist-info/METADATA
odoo14_addon_ssi_product_website-14.0.1.2.0.dist-info/WHEEL
odoo14_addon_ssi_product_website-14.0.1.2.0.dist-info/top_level.txt
odoo14_addon_ssi_product_website-14.0.1.2.0.dist-info/RECORD
